MANIFEST.in
README.rst
requirements.txt
setup.cfg
setup.py
graphene_peewee_async/__init__.py
graphene_peewee_async/converter.py
graphene_peewee_async/fields.py
graphene_peewee_async/mutations.py
graphene_peewee_async/queries.py
graphene_peewee_async/registry.py
graphene_peewee_async/types.py
graphene_peewee_async/utils.py
graphene_peewee_async.egg-info/PKG-INFO
graphene_peewee_async.egg-info/SOURCES.txt
graphene_peewee_async.egg-info/dependency_links.txt
graphene_peewee_async.egg-info/not-zip-safe
graphene_peewee_async.egg-info/requires.txt
graphene_peewee_async.egg-info/top_level.txt
tests/common/__init__.py
tests/common/api_test.py
tests/common/base_test.py
tests/common/models.py
tests/common/schema.py
tests/test_api/__init__.py
tests/test_api/test_clone_mutation.py
tests/test_api/test_create_mutation.py
tests/test_api/test_delete_mutation.py
tests/test_api/test_query.py
tests/test_api/test_update_mutation.py