Metadata-Version: 1.1
Name: graphene-peewee-async
Version: 2.1.4
Summary: Graphene peewee-async integration
Home-page: https://github.com/insolite/graphene-peewee-async
Author: Oleg Krasnikov
Author-email: a.insolite@gmail.com
License: MIT
Keywords: api graphql protocol rest relay graphene
Platform: any
Classifier: Development Status :: 3 - Alpha
Classifier: Intended Audience :: Developers
Classifier: Topic :: Software Development :: Libraries
Classifier: Programming Language :: Python :: 3
Classifier: Programming Language :: Python :: 3.4
Classifier: Programming Language :: Python :: 3.5
Classifier: Programming Language :: Python :: Implementation :: PyPy
